Tamako/Tamako.py
Tamako/__init__.py
Tamako/bivariate.py
Tamako/determinant_eigen.py
Tamako/fittedLinear.py
Tamako/func_solv.py
Tamako/independent_dependent.py
Tamako/plot_func.py
Tamako.py-0.7.dist-info/LICENSE
Tamako.py-0.7.dist-info/METADATA
Tamako.py-0.7.dist-info/WHEEL
Tamako.py-0.7.dist-info/top_level.txt
Tamako.py-0.7.dist-info/RECORD
