Metadata-Version: 2.1
Name: Tamako.py
Version: 0.7
Summary: Simple API Wrapper for Tamako API.
Home-page: https://github.com/Tamako-Tech/Tamako.py
Author: Tamako.Tech
License: UNKNOWN
Platform: UNKNOWN
Classifier: Programming Language :: Python :: 3
Classifier: License :: OSI Approved :: MIT License
Classifier: Operating System :: OS Independent
Requires-Python: >= 3.6
Requires-Dist: requests
